AngPoly3D/__init__.py
AngPoly3D/ang_poly3d.py
AngPoly3D/calc_ang_poly3d.py
AngPoly3D-0.0.1.dist-info/LICENSE
AngPoly3D-0.0.1.dist-info/METADATA
AngPoly3D-0.0.1.dist-info/WHEEL
AngPoly3D-0.0.1.dist-info/entry_points.txt
AngPoly3D-0.0.1.dist-info/top_level.txt
AngPoly3D-0.0.1.dist-info/RECORD
