Metadata-Version: 2.1
Name: AngPoly3D
Version: 0.0.1
Summary: A Python package to calculate the angle between the oreintation of a particle and a global reference orientation considering the particle's point group symmetry
Home-page: https://github.com/sumitavakundu007/AngPoly3D
Author: Sumitava Kundu
Author-email: kundusumitava@gmail.com
License: UNKNOWN
Project-URL: Bug Reports, https://github.com/sumitavakundu007/AngPoly3D/issues
Project-URL: Say Thanks!, http://saythanks.io/to/example
Project-URL: Source, https://github.com/sumitavakundu007/AngPoly3D/
Keywords: sample,setuptools,development
Platform: UNKNOWN
Classifier: Intended Audience :: Developers
Classifier: Topic :: Software Development :: Build Tools
Classifier: License :: OSI Approved :: MIT License
Classifier: Programming Language :: Python :: 3
Classifier: Programming Language :: Python :: 3.6
Classifier: Programming Language :: Python :: 3.7
Classifier: Programming Language :: Python :: 3.8
Classifier: Programming Language :: Python :: 3.9
Requires-Python: >=3.6
License-File: LICENSE
Requires-Dist: rowan
